fuzz_utils/__init__.py
fuzz_utils/main.py
fuzz_utils/generate/FoundryTest.py
fuzz_utils/generate/__init__.py
fuzz_utils/generate/fuzzers/Echidna.py
fuzz_utils/generate/fuzzers/Medusa.py
fuzz_utils/generate/fuzzers/__init__.py
fuzz_utils/parsing/__init__.py
fuzz_utils/parsing/parser.py
fuzz_utils/parsing/parser_util.py
fuzz_utils/parsing/commands/__init__.py
fuzz_utils/parsing/commands/generate.py
fuzz_utils/parsing/commands/init.py
fuzz_utils/parsing/commands/template.py
fuzz_utils/template/HarnessGenerator.py
fuzz_utils/template/__init__.py
fuzz_utils/templates/__init__.py
fuzz_utils/templates/default_config.py
fuzz_utils/templates/foundry_templates.py
fuzz_utils/templates/harness_templates.py
fuzz_utils/utils/__init__.py
fuzz_utils/utils/crytic_print.py
fuzz_utils/utils/encoding.py
fuzz_utils/utils/error_handler.py
fuzz_utils/utils/file_manager.py
fuzz_utils/utils/remappings.py
fuzz_utils/utils/slither_utils.py
tests/__init__.py
tests/conftest.py
tests/test_harness.py
tests/test_remapping_detection.py
tests/test_types_echidna.py
tests/test_types_medusa.py
fuzz_utils-0.2.0.dist-info/LICENSE
fuzz_utils-0.2.0.dist-info/METADATA
fuzz_utils-0.2.0.dist-info/WHEEL
fuzz_utils-0.2.0.dist-info/entry_points.txt
fuzz_utils-0.2.0.dist-info/top_level.txt
fuzz_utils-0.2.0.dist-info/RECORD
