Metadata-Version: 2.1
Name: fuzz-utils
Version: 0.2.0
Summary: A tool for automatically generating unit tests from Echidna and Medusa reproducers.
Author: Trail of Bits
License: AGPL-3.0
Project-URL: Homepage, https://github.com/crytic/fuzz-utils
Requires-Python: >=3.10
License-File: LICENSE
Requires-Dist: colorama >=0.4.0
Requires-Dist: slither-analyzer >=0.10.0
Requires-Dist: jinja2 >=3.1.0
Requires-Dist: eth-abi >=5.0.1
Requires-Dist: eth-utils >=4.0.0
Requires-Dist: eth-typing >=4.0.0
Provides-Extra: dev
Requires-Dist: fuzz-utils[lint,test] ; extra == 'dev'
Provides-Extra: lint
Requires-Dist: pylint ==2.13.4 ; extra == 'lint'
Requires-Dist: black ==22.3.0 ; extra == 'lint'
Provides-Extra: test
Requires-Dist: pytest ; extra == 'test'
Requires-Dist: solc-select >=0.1.4 ; extra == 'test'
